{
    "categories": [
                   {
                   "id": "1",
                   "level": 1,
                   "title": "Application",
                   "isParent": "true",
                   "childern": [
                                {
                                "id": "1.1",
                                "title": "Boxes - packing boxes and crates",
                                "isParent": "false",
                                "Items": [
                                          {
                                          "id": "1",
                                          "title": "Ara",
                                          "description": "The common Malaysian name for the timber of Ficus spp. (Moraceae). Vernacular names applied include arah (Sabah) and kayuara (Sabah). Major species include F. callosa, F. fistulosa, F. lamponga, F. magnoliifolia, F. microcarpa, F. racemosa, F. sundaica, F. superba, F. tinctoria, F. variegata, F. vasculosa, F. virens and F. viridicarpa. The sapwood is not differentiated from the heartwood, which is light yellow-brown or in various shades of yellow to pink-grey.Also known as Fig (India); Ara, Bunut, Karet and Kundang (Indonesia); Deua kiang, Mai deaua kham and Mai do (Laos); Nyaung (Myanmar); Papua New Guinea fig (Papua New Guinea);Balete (Philippines); Sai (Thailand); and Chi da and Sung (Vietnam)."
                                          },
                                          {
                                          "id": "2",
                                          "title": "Balek Angin",
                                          "description": "The common Malaysian name for the timber of Mallotus spp. (Euphorbiaceae). Vernacular names applied include balek angin bopeng (Peninsular Malaysia), enserai (Sarawak), mallotus (Sabah) with various epithets, perupok (Peninsular Malaysia), selung apid (Sabah), serapoh (Peninsular Malaysia), singin (Sarawak) and ulas (Sabah). Major species include M. leucodermis, M. miquelianus, M. muticus and M. wrayi. The sapwood is not differentiated from the heartwood, which is straw-coloured.Also known as Kamala (Australia); Raini (India); Balek angin, Biraki, Ki mejong, Kolimama poete, Morotokoelo, Ota mewoeloe, Tofa, Towoela and Tunbuwat (Indonesia); Banato, Hinlaumo and Tula tula(Philippines); and Vang (Vietnam)."
                                          },
                                          {
                                          "id": "3",
                                          "title": "Bebuta",
                                          "description": "The common Malaysian name for the timber of Excoecaria spp. (Euphorbiaceae). Vernacular names applied include buta-buta (Peninsular Malaysia and Sabah). Only one species attains timber size, viz. E. agallocha. The straw-coloured sapwood is normally not differentiated from the heartwood, which is pink-white to pale brown in colour.Also known as Geon (India); Bintaos laut, Kokoboeta, Menengan and Penggung (Indonesia); Gewa (Pakistan); Buta-buta (Philippines); Tatum (Thailand); and Gia (Vietnam)."
                                          },
                                          {
                                          "id": "4",
                                          "title": "Berangan",
                                          "description": "The Standard Malaysian Name for the timber of Castanopsis spp. (Fagaceae). Vernacular names applied include berangan (Peninsular Malaysia, Sabah and Sarawak) with various epithets, kogopon (Sabah), maruwit (Sarawak) and various other localised names too numerous to be listed here. Major species include C. borneensis, C. buruana, C. clemensii, C.curtisii, C. endertii, C. evansii, C. foxworthyi, C. fulva, C. hypophoenicea, C. inermis, C. javanica, C. malaccensis, C.microphylla, C. motleyana, C. oviformis, C. paucispina, C. psilophylla, C. rhamnifolia and C. schefferiana. The sapwood is light brown, often with a greenish tinge and sharply defined from the heartwood, which is dark brown or dark red-brown.Also know as Indian chestnut (India); Saninten (Indonesia); Fan, Ko and Ko deng (Laos); Katia (Mynmar); New Guinea oak (Papua New Guinea); Gasa and Philippines chestnut (Philippines); Khoduiy, Kholaem, Ko and Ko nam (Thailand); and Ca-oi (Vietnam)."
                                          },
                                          {
                                          "id": "5",
                                          "title": "Binuang",
                                          "description": "The Standard Malaysian Name for the timber of Octomeles sumatrana (Datiscaceae). Vernacular name applied appears to be rather uniform in that only binuang is used throughout the country. Only one species has been recorded in the country. The sapwood is white with a greyish tinge and is moderately sharply defined from the heartwood which is buff to pale brown or sometimes pinkish brown.Also known as Banuang, Benoea, Benuang, Binuang bini and Winuang (Indonesia); Erima, Ilimo and Irima (Papua New Guinea); and Barong, Barousan, Bilus and Binuang (Philippines)."
                                          },
                                          {
                                          "id": "6",
                                          "title": "Dedali",
                                          "description": "The Standard Malaysian Name as well as the ASEAN Standard name for the timber of Strombosia javanica (Olacaceae). Vernacular names applied include bayam badak (Kedah, Perak and Pahang) and belian landak (Sarawak). This is a monotypic timber. The sapwood is lighter in colour than the heartwood and is moderately sharply defined from the heartwood, which is pale yellow with an olive-brown tinge, darkening to light orange-brown.Also known as Entelung and Kayu Kacang (Indonesia); and Banata (Myanmar)."
                                          },
                                          {
                                          "id": "7",
                                          "title": "Gaham Badak",
                                          "description": "The common Malaysian name for the timber of Blumeodendron spp. (Euphorbiaceae). The ASEAN Standard Name for the timber, which is of Indonesian origin, is TENGKURUNG. Vernacular names applied to the timber include gangulang (Sabah), gelugor hutan (Peninsular Malaysia), medang lempong (Peninsular Malaysia) and merbulan (Sarawak). Major species include B. kurzii and B. tokbrai. The heartwood, which is light brown in colour, is not distinct from the lighter coloured sapwood. Occasionally, a corewood of darker brown with black streaks is produced.Also known as Tengkurung (Indonesia); and Lindog (Philippines)."
                                          }
                                          ],
                                "childern": []
                                },
                                {
                                "id": "1.2",
                                "title": "Building construction",
                                "isParent": "true",
                                "Items": [],
                                "childern": [
                                             {
                                             "id": "1.2.1",
                                             "isParent": "false",
                                             "title": "Column – heavy duty",
                                             "Items": [
                                                       {
                                                       "id": "36",
                                                       "title": "Ara",
                                                       "description": "The common Malaysian name for the timber of Ficus spp. (Moraceae). Vernacular names applied include arah (Sabah) and kayuara (Sabah). Major species include F. callosa, F. fistulosa, F. lamponga, F. magnoliifolia, F. microcarpa, F. racemosa, F. sundaica, F. superba, F. tinctoria, F. variegata, F. vasculosa, F. virens and F. viridicarpa. The sapwood is not differentiated from the heartwood, which is light yellow-brown or in various shades of yellow to pink-grey.Also known as Fig (India); Ara, Bunut, Karet and Kundang (Indonesia); Deua kiang, Mai deaua kham and Mai do (Laos); Nyaung (Myanmar); Papua New Guinea fig (Papua New Guinea);Balete (Philippines); Sai (Thailand); and Chi da and Sung (Vietnam)."
                                                       },
                                                       {
                                                       "id": "37",
                                                       "title": "Balek Angin",
                                                       "description": "The common Malaysian name for the timber of Mallotus spp. (Euphorbiaceae). Vernacular names applied include balek angin bopeng (Peninsular Malaysia), enserai (Sarawak), mallotus (Sabah) with various epithets, perupok (Peninsular Malaysia), selung apid (Sabah), serapoh (Peninsular Malaysia), singin (Sarawak) and ulas (Sabah). Major species include M. leucodermis, M. miquelianus, M. muticus and M. wrayi. The sapwood is not differentiated from the heartwood, which is straw-coloured.Also known as Kamala (Australia); Raini (India); Balek angin, Biraki, Ki mejong, Kolimama poete, Morotokoelo, Ota mewoeloe, Tofa, Towoela and Tunbuwat (Indonesia); Banato, Hinlaumo and Tula tula(Philippines); and Vang (Vietnam)."
                                                       },
                                                       {
                                                       "id": "38",
                                                       "title": "Bebuta",
                                                       "description": "The common Malaysian name for the timber of Excoecaria spp. (Euphorbiaceae). Vernacular names applied include buta-buta (Peninsular Malaysia and Sabah). Only one species attains timber size, viz. E. agallocha. The straw-coloured sapwood is normally not differentiated from the heartwood, which is pink-white to pale brown in colour.Also known as Geon (India); Bintaos laut, Kokoboeta, Menengan and Penggung (Indonesia); Gewa (Pakistan); Buta-buta (Philippines); Tatum (Thailand); and Gia (Vietnam)."
                                                       },
                                                       {
                                                       "id": "39",
                                                       "title": "Berangan",
                                                       "description": "The Standard Malaysian Name for the timber of Castanopsis spp. (Fagaceae). Vernacular names applied include berangan (Peninsular Malaysia, Sabah and Sarawak) with various epithets, kogopon (Sabah), maruwit (Sarawak) and various other localised names too numerous to be listed here. Major species include C. borneensis, C. buruana, C. clemensii, C.curtisii, C. endertii, C. evansii, C. foxworthyi, C. fulva, C. hypophoenicea, C. inermis, C. javanica, C. malaccensis, C.microphylla, C. motleyana, C. oviformis, C. paucispina, C. psilophylla, C. rhamnifolia and C. schefferiana. The sapwood is light brown, often with a greenish tinge and sharply defined from the heartwood, which is dark brown or dark red-brown.Also know as Indian chestnut (India); Saninten (Indonesia); Fan, Ko and Ko deng (Laos); Katia (Mynmar); New Guinea oak (Papua New Guinea); Gasa and Philippines chestnut (Philippines); Khoduiy, Kholaem, Ko and Ko nam (Thailand); and Ca-oi (Vietnam)."
                                                       },
                                                       {
                                                       "id": "40",
                                                       "title": "Binuang",
                                                       "description": "The Standard Malaysian Name for the timber of Octomeles sumatrana (Datiscaceae). Vernacular name applied appears to be rather uniform in that only binuang is used throughout the country. Only one species has been recorded in the country. The sapwood is white with a greyish tinge and is moderately sharply defined from the heartwood which is buff to pale brown or sometimes pinkish brown.Also known as Banuang, Benoea, Benuang, Binuang bini and Winuang (Indonesia); Erima, Ilimo and Irima (Papua New Guinea); and Barong, Barousan, Bilus and Binuang (Philippines)."
                                                       },
                                                       {
                                                       "id": "41",
                                                       "title": "Dedali",
                                                       "description": "The Standard Malaysian Name as well as the ASEAN Standard name for the timber of Strombosia javanica (Olacaceae). Vernacular names applied include bayam badak (Kedah, Perak and Pahang) and belian landak (Sarawak). This is a monotypic timber. The sapwood is lighter in colour than the heartwood and is moderately sharply defined from the heartwood, which is pale yellow with an olive-brown tinge, darkening to light orange-brown.Also known as Entelung and Kayu Kacang (Indonesia); and Banata (Myanmar)."
                                                       },
                                                       {
                                                       "id": "42",
                                                       "title": "Gaham Badak",
                                                       "description": "The common Malaysian name for the timber of Blumeodendron spp. (Euphorbiaceae). The ASEAN Standard Name for the timber, which is of Indonesian origin, is TENGKURUNG. Vernacular names applied to the timber include gangulang (Sabah), gelugor hutan (Peninsular Malaysia), medang lempong (Peninsular Malaysia) and merbulan (Sarawak). Major species include B. kurzii and B. tokbrai. The heartwood, which is light brown in colour, is not distinct from the lighter coloured sapwood. Occasionally, a corewood of darker brown with black streaks is produced.Also known as Tengkurung (Indonesia); and Lindog (Philippines)."
                                                       }
                                                       ]
                                             },
                                             {
                                             "id": "1.2.2",
                                             "title": "Column – light duty",
                                             "isParent": "false",
                                             "items": [
                                                       {
                                                       "id": "1",
                                                       "titile": "",
                                                       "description": ""
                                                       },
                                                       {
                                                       "id": "2",
                                                       "titile": "",
                                                       "description": ""
                                                       },
                                                       {
                                                       "id": "3",
                                                       "titile": "",
                                                       "description": ""
                                                       },
                                                       {
                                                       "id": "4",
                                                       "titile": "",
                                                       "description": ""
                                                       },
                                                       {
                                                       "id": "5",
                                                       "titile": "",
                                                       "description": ""
                                                       }
                                                       ]
                                             },
                                             {
                                             "id": "1.2.3",
                                             "title": "Door and window frames and sills",
                                             "isParent": "false",
                                             "items": []
                                             },
                                             {
                                             "id": "1.2.4",
                                             "title": "Flooring – general",
                                             "isParent": "false",
                                             "items": [
                                                       {
                                                       "id": "1",
                                                       "titile": "",
                                                       "description": ""
                                                       },
                                                       {
                                                       "id": "2",
                                                       "titile": "",
                                                       "description": ""
                                                       },
                                                       {
                                                       "id": "3",
                                                       "titile": "",
                                                       "description": ""
                                                       },
                                                       {
                                                       "id": "4",
                                                       "titile": "",
                                                       "description": ""
                                                       },
                                                       {
                                                       "id": "5",
                                                       "titile": "",
                                                       "description": ""
                                                       }
                                                       ]
                                             },
                                             {
                                             "id": "1.2.5",
                                             "title": "Flooring – heavy traffic",
                                             "isParent": "false",
                                             "items": []
                                             },
                                             {
                                             "id": "1.2.6",
                                             "title": "Foundation piling",
                                             "isParent": "false",
                                             "items": [
                                                       {
                                                       "id": "1",
                                                       "titile": "",
                                                       "description": ""
                                                       },
                                                       {
                                                       "id": "2",
                                                       "titile": "",
                                                       "description": ""
                                                       },
                                                       {
                                                       "id": "3",
                                                       "titile": "",
                                                       "description": ""
                                                       },
                                                       {
                                                       "id": "4",
                                                       "titile": "",
                                                       "description": ""
                                                       },
                                                       {
                                                       "id": "5",
                                                       "titile": "",
                                                       "description": ""
                                                       }
                                                       ]
                                             }
                                             ]
                                },
                                {
                                "id": "1.3",
                                "title": "Carving",
                                "isParent": "false",
                                "Items": [
                                          {
                                          "id": "8",
                                          "title": "Baru",
                                          "description": "The common Malaysian name for the timber of Hibiscus spp. and Thespesia populnea (Malvaceae). Vernacular names applied include baru-baru (Peninsular Malaysia), baru laut (Sabah), bebaru (Peninsular Malaysia), bebaru bulu (Peninsular Malaysia), kali bang-bang (Sabah), kangsar (Peninsular Malaysia), langkubing (Sarawak), randog (Sabah) and tutor (Peninsular Malaysia). Major species include Hibiscus borneensis, H. campylosiphon, H. floccosus, H. macrophyllus, H. tiliaceus; and Thespesia populnea. The sapwood ranges from white to light yellow and is not defined to sharply defined from the heartwood, which varies from light yellow, light grey-brown, grey-black, purple black to red brown.Also known as Baru, Bontoe, Waru, Waru gunong and Waroe (Indonesia); Silver hibiscus (Papua New Guinea); Gummamela de arana and Malubago (Philippines); and Ehaba (Thailand)."
                                          },
                                          {
                                          "id": "9",
                                          "title": "Chengal",
                                          "description": "The common Malaysian name for the timber of Mallotus spp. (Euphorbiaceae). Vernacular names applied include balek angin bopeng (Peninsular Malaysia), enserai (Sarawak), mallotus (Sabah) with various epithets, perupok (Peninsular Malaysia), selung apid (Sabah), serapoh (Peninsular Malaysia), singin (Sarawak) and ulas (Sabah). Major species include M. leucodermis, M. miquelianus, M. muticus and M. wrayi. The sapwood is not differentiated from the heartwood, which is straw-coloured.Also known as Kamala (Australia); Raini (India); Balek angin, Biraki, Ki mejong, Kolimama poete, Morotokoelo, Ota mewoeloe, Tofa, Towoela and Tunbuwat (Indonesia); Banato, Hinlaumo and Tula tula(Philippines); and Vang (Vietnam)."
                                          },
                                          {
                                          "id": "10",
                                          "title": "Dedap",
                                          "description": "The common Malaysian name for the timber of Excoecaria spp. (Euphorbiaceae). Vernacular names applied include buta-buta (Peninsular Malaysia and Sabah). Only one species attains timber size, viz. E. agallocha. The straw-coloured sapwood is normally not differentiated from the heartwood, which is pink-white to pale brown in colour.Also known as Geon (India); Bintaos laut, Kokoboeta, Menengan and Penggung (Indonesia); Gewa (Pakistan); Buta-buta (Philippines); Tatum (Thailand); and Gia (Vietnam)."
                                          },
                                          {
                                          "id": "11",
                                          "title": "Derum",
                                          "description": "The Standard Malaysian Name for the timber of Castanopsis spp. (Fagaceae). Vernacular names applied include berangan (Peninsular Malaysia, Sabah and Sarawak) with various epithets, kogopon (Sabah), maruwit (Sarawak) and various other localised names too numerous to be listed here. Major species include C. borneensis, C. buruana, C. clemensii, C.curtisii, C. endertii, C. evansii, C. foxworthyi, C. fulva, C. hypophoenicea, C. inermis, C. javanica, C. malaccensis, C.microphylla, C. motleyana, C. oviformis, C. paucispina, C. psilophylla, C. rhamnifolia and C. schefferiana. The sapwood is light brown, often with a greenish tinge and sharply defined from the heartwood, which is dark brown or dark red-brown.Also know as Indian chestnut (India); Saninten (Indonesia); Fan, Ko and Ko deng (Laos); Katia (Mynmar); New Guinea oak (Papua New Guinea); Gasa and Philippines chestnut (Philippines); Khoduiy, Kholaem, Ko and Ko nam (Thailand); and Ca-oi (Vietnam)."
                                          },
                                          {
                                          "id": "12",
                                          "title": "Gading",
                                          "description": "The common Malaysian name for the timber of Excoecaria spp. (Euphorbiaceae). Vernacular names applied include buta-buta (Peninsular Malaysia and Sabah). Only one species attains timber size, viz. E. agallocha. The straw-coloured sapwood is normally not differentiated from the heartwood, which is pink-white to pale brown in colour.Also known as Geon (India); Bintaos laut, Kokoboeta, Menengan and Penggung (Indonesia); Gewa (Pakistan); Buta-buta (Philippines); Tatum (Thailand); and Gia (Vietnam)."
                                          },
                                          {
                                          "id": "13",
                                          "title": "Jelutong",
                                          "description": "The common Malaysian name for the timber of Excoecaria spp. (Euphorbiaceae). Vernacular names applied include buta-buta (Peninsular Malaysia and Sabah). Only one species attains timber size, viz. E. agallocha. The straw-coloured sapwood is normally not differentiated from the heartwood, which is pink-white to pale brown in colour.Also known as Geon (India); Bintaos laut, Kokoboeta, Menengan and Penggung (Indonesia); Gewa (Pakistan); Buta-buta (Philippines); Tatum (Thailand); and Gia (Vietnam)."
                                          },
                                          {
                                          "id": "14",
                                          "title": "Jelutong Pipit",
                                          "description": "The common Malaysian name for the timber of Excoecaria spp. (Euphorbiaceae). Vernacular names applied include buta-buta (Peninsular Malaysia and Sabah). Only one species attains timber size, viz. E. agallocha. The straw-coloured sapwood is normally not differentiated from the heartwood, which is pink-white to pale brown in colour.Also known as Geon (India); Bintaos laut, Kokoboeta, Menengan and Penggung (Indonesia); Gewa (Pakistan); Buta-buta (Philippines); Tatum (Thailand); and Gia (Vietnam)."
                                          }
                                          ],
                                "childern": []
                                },
                                {
                                "id": "1.4",
                                "title": "Cooling tower ",
                                "isParent": "true",
                                "Items": [],
                                "childern": []
                                },
                                {
                                "id": "1.5",
                                "title": "Decking",
                                "isParent": "false",
                                "Items": [
                                          {
                                          "id": "15",
                                          "title": "Baru",
                                          "description": "The common Malaysian name for the timber of Hibiscus spp. and Thespesia populnea (Malvaceae). Vernacular names applied include baru-baru (Peninsular Malaysia), baru laut (Sabah), bebaru (Peninsular Malaysia), bebaru bulu (Peninsular Malaysia), kali bang-bang (Sabah), kangsar (Peninsular Malaysia), langkubing (Sarawak), randog (Sabah) and tutor (Peninsular Malaysia). Major species include Hibiscus borneensis, H. campylosiphon, H. floccosus, H. macrophyllus, H. tiliaceus; and Thespesia populnea. The sapwood ranges from white to light yellow and is not defined to sharply defined from the heartwood, which varies from light yellow, light grey-brown, grey-black, purple black to red brown.Also known as Baru, Bontoe, Waru, Waru gunong and Waroe (Indonesia); Silver hibiscus (Papua New Guinea); Gummamela de arana and Malubago (Philippines); and Ehaba (Thailand)."
                                          },
                                          {
                                          "id": "16",
                                          "title": "Chengal",
                                          "description": "The common Malaysian name for the timber of Mallotus spp. (Euphorbiaceae). Vernacular names applied include balek angin bopeng (Peninsular Malaysia), enserai (Sarawak), mallotus (Sabah) with various epithets, perupok (Peninsular Malaysia), selung apid (Sabah), serapoh (Peninsular Malaysia), singin (Sarawak) and ulas (Sabah). Major species include M. leucodermis, M. miquelianus, M. muticus and M. wrayi. The sapwood is not differentiated from the heartwood, which is straw-coloured.Also known as Kamala (Australia); Raini (India); Balek angin, Biraki, Ki mejong, Kolimama poete, Morotokoelo, Ota mewoeloe, Tofa, Towoela and Tunbuwat (Indonesia); Banato, Hinlaumo and Tula tula(Philippines); and Vang (Vietnam)."
                                          },
                                          {
                                          "id": "17",
                                          "title": "Dedap",
                                          "description": "The common Malaysian name for the timber of Excoecaria spp. (Euphorbiaceae). Vernacular names applied include buta-buta (Peninsular Malaysia and Sabah). Only one species attains timber size, viz. E. agallocha. The straw-coloured sapwood is normally not differentiated from the heartwood, which is pink-white to pale brown in colour.Also known as Geon (India); Bintaos laut, Kokoboeta, Menengan and Penggung (Indonesia); Gewa (Pakistan); Buta-buta (Philippines); Tatum (Thailand); and Gia (Vietnam)."
                                          },
                                          {
                                          "id": "18",
                                          "title": "Derum",
                                          "description": "The Standard Malaysian Name for the timber of Castanopsis spp. (Fagaceae). Vernacular names applied include berangan (Peninsular Malaysia, Sabah and Sarawak) with various epithets, kogopon (Sabah), maruwit (Sarawak) and various other localised names too numerous to be listed here. Major species include C. borneensis, C. buruana, C. clemensii, C.curtisii, C. endertii, C. evansii, C. foxworthyi, C. fulva, C. hypophoenicea, C. inermis, C. javanica, C. malaccensis, C.microphylla, C. motleyana, C. oviformis, C. paucispina, C. psilophylla, C. rhamnifolia and C. schefferiana. The sapwood is light brown, often with a greenish tinge and sharply defined from the heartwood, which is dark brown or dark red-brown.Also know as Indian chestnut (India); Saninten (Indonesia); Fan, Ko and Ko deng (Laos); Katia (Mynmar); New Guinea oak (Papua New Guinea); Gasa and Philippines chestnut (Philippines); Khoduiy, Kholaem, Ko and Ko nam (Thailand); and Ca-oi (Vietnam)."
                                          },
                                          {
                                          "id": "19",
                                          "title": "Gading",
                                          "description": "The common Malaysian name for the timber of Excoecaria spp. (Euphorbiaceae). Vernacular names applied include buta-buta (Peninsular Malaysia and Sabah). Only one species attains timber size, viz. E. agallocha. The straw-coloured sapwood is normally not differentiated from the heartwood, which is pink-white to pale brown in colour.Also known as Geon (India); Bintaos laut, Kokoboeta, Menengan and Penggung (Indonesia); Gewa (Pakistan); Buta-buta (Philippines); Tatum (Thailand); and Gia (Vietnam)."
                                          },
                                          {
                                          "id": "20",
                                          "title": "Jelutong",
                                          "description": "The common Malaysian name for the timber of Excoecaria spp. (Euphorbiaceae). Vernacular names applied include buta-buta (Peninsular Malaysia and Sabah). Only one species attains timber size, viz. E. agallocha. The straw-coloured sapwood is normally not differentiated from the heartwood, which is pink-white to pale brown in colour.Also known as Geon (India); Bintaos laut, Kokoboeta, Menengan and Penggung (Indonesia); Gewa (Pakistan); Buta-buta (Philippines); Tatum (Thailand); and Gia (Vietnam)."
                                          },
                                          {
                                          "id": "21",
                                          "title": "Jelutong Pipit",
                                          "description": "The common Malaysian name for the timber of Excoecaria spp. (Euphorbiaceae). Vernacular names applied include buta-buta (Peninsular Malaysia and Sabah). Only one species attains timber size, viz. E. agallocha. The straw-coloured sapwood is normally not differentiated from the heartwood, which is pink-white to pale brown in colour.Also known as Geon (India); Bintaos laut, Kokoboeta, Menengan and Penggung (Indonesia); Gewa (Pakistan); Buta-buta (Philippines); Tatum (Thailand); and Gia (Vietnam)."
                                          }
                                          ],
                                "childern": []
                                },
                                {
                                "id": "1.6",
                                "title": "Disposable chopsticks",
                                "isParent": "true",
                                "Items": [],
                                "childern": []
                                },
                                {
                                "id": "1.7",
                                "title": "  Fender supports",
                                "isParent": "false",
                                "Items": [],
                                "childern": []
                                },
                                {
                                "id": "1.8",
                                "title": "Furniture",
                                "isParent": "true",
                                "Items": [],
                                "childern": []
                                },
                                {
                                "id": "1.9",
                                "title": "Joinery and cabinet making",
                                "isParent": "false",
                                "Items": [
                                          {
                                          "id": "22",
                                          "title": "Baru",
                                          "description": "The common Malaysian name for the timber of Hibiscus spp. and Thespesia populnea (Malvaceae). Vernacular names applied include baru-baru (Peninsular Malaysia), baru laut (Sabah), bebaru (Peninsular Malaysia), bebaru bulu (Peninsular Malaysia), kali bang-bang (Sabah), kangsar (Peninsular Malaysia), langkubing (Sarawak), randog (Sabah) and tutor (Peninsular Malaysia). Major species include Hibiscus borneensis, H. campylosiphon, H. floccosus, H. macrophyllus, H. tiliaceus; and Thespesia populnea. The sapwood ranges from white to light yellow and is not defined to sharply defined from the heartwood, which varies from light yellow, light grey-brown, grey-black, purple black to red brown.Also known as Baru, Bontoe, Waru, Waru gunong and Waroe (Indonesia); Silver hibiscus (Papua New Guinea); Gummamela de arana and Malubago (Philippines); and Ehaba (Thailand)."
                                          },
                                          {
                                          "id": "23",
                                          "title": "Chengal",
                                          "description": "The common Malaysian name for the timber of Mallotus spp. (Euphorbiaceae). Vernacular names applied include balek angin bopeng (Peninsular Malaysia), enserai (Sarawak), mallotus (Sabah) with various epithets, perupok (Peninsular Malaysia), selung apid (Sabah), serapoh (Peninsular Malaysia), singin (Sarawak) and ulas (Sabah). Major species include M. leucodermis, M. miquelianus, M. muticus and M. wrayi. The sapwood is not differentiated from the heartwood, which is straw-coloured.Also known as Kamala (Australia); Raini (India); Balek angin, Biraki, Ki mejong, Kolimama poete, Morotokoelo, Ota mewoeloe, Tofa, Towoela and Tunbuwat (Indonesia); Banato, Hinlaumo and Tula tula(Philippines); and Vang (Vietnam)."
                                          },
                                          {
                                          "id": "24",
                                          "title": "Dedap",
                                          "description": "The common Malaysian name for the timber of Excoecaria spp. (Euphorbiaceae). Vernacular names applied include buta-buta (Peninsular Malaysia and Sabah). Only one species attains timber size, viz. E. agallocha. The straw-coloured sapwood is normally not differentiated from the heartwood, which is pink-white to pale brown in colour.Also known as Geon (India); Bintaos laut, Kokoboeta, Menengan and Penggung (Indonesia); Gewa (Pakistan); Buta-buta (Philippines); Tatum (Thailand); and Gia (Vietnam)."
                                          },
                                          {
                                          "id": "25",
                                          "title": "Derum",
                                          "description": "The Standard Malaysian Name for the timber of Castanopsis spp. (Fagaceae). Vernacular names applied include berangan (Peninsular Malaysia, Sabah and Sarawak) with various epithets, kogopon (Sabah), maruwit (Sarawak) and various other localised names too numerous to be listed here. Major species include C. borneensis, C. buruana, C. clemensii, C.curtisii, C. endertii, C. evansii, C. foxworthyi, C. fulva, C. hypophoenicea, C. inermis, C. javanica, C. malaccensis, C.microphylla, C. motleyana, C. oviformis, C. paucispina, C. psilophylla, C. rhamnifolia and C. schefferiana. The sapwood is light brown, often with a greenish tinge and sharply defined from the heartwood, which is dark brown or dark red-brown.Also know as Indian chestnut (India); Saninten (Indonesia); Fan, Ko and Ko deng (Laos); Katia (Mynmar); New Guinea oak (Papua New Guinea); Gasa and Philippines chestnut (Philippines); Khoduiy, Kholaem, Ko and Ko nam (Thailand); and Ca-oi (Vietnam)."
                                          },
                                          {
                                          "id": "26",
                                          "title": "Gading",
                                          "description": "The common Malaysian name for the timber of Excoecaria spp. (Euphorbiaceae). Vernacular names applied include buta-buta (Peninsular Malaysia and Sabah). Only one species attains timber size, viz. E. agallocha. The straw-coloured sapwood is normally not differentiated from the heartwood, which is pink-white to pale brown in colour.Also known as Geon (India); Bintaos laut, Kokoboeta, Menengan and Penggung (Indonesia); Gewa (Pakistan); Buta-buta (Philippines); Tatum (Thailand); and Gia (Vietnam)."
                                          },
                                          {
                                          "id": "27",
                                          "title": "Jelutong",
                                          "description": "The common Malaysian name for the timber of Excoecaria spp. (Euphorbiaceae). Vernacular names applied include buta-buta (Peninsular Malaysia and Sabah). Only one species attains timber size, viz. E. agallocha. The straw-coloured sapwood is normally not differentiated from the heartwood, which is pink-white to pale brown in colour.Also known as Geon (India); Bintaos laut, Kokoboeta, Menengan and Penggung (Indonesia); Gewa (Pakistan); Buta-buta (Philippines); Tatum (Thailand); and Gia (Vietnam)."
                                          },
                                          {
                                          "id": "28",
                                          "title": "Jelutong Pipit",
                                          "description": "The common Malaysian name for the timber of Excoecaria spp. (Euphorbiaceae). Vernacular names applied include buta-buta (Peninsular Malaysia and Sabah). Only one species attains timber size, viz. E. agallocha. The straw-coloured sapwood is normally not differentiated from the heartwood, which is pink-white to pale brown in colour.Also known as Geon (India); Bintaos laut, Kokoboeta, Menengan and Penggung (Indonesia); Gewa (Pakistan); Buta-buta (Philippines); Tatum (Thailand); and Gia (Vietnam)."
                                          }
                                          ],
                                "childern": []
                                },
                                {
                                "id": "1.10",
                                "title": "Marine construction – wharves and other related construction",
                                "isParent": "true",
                                "Items": [],
                                "childern": []
                                }
                                ]
                   },
                   {
                   "id": "2",
                   "level": 1,
                   "title": "Machining Properties",
                   "isParent": "true",
                   "childern": [
                                {
                                "id": "2.1",
                                "title": "Boring ",
                                "isParent": "true",
                                "Items": [
                                          {
                                          "id": "29",
                                          "title": "Ara",
                                          "description": "The common Malaysian name for the timber of Ficus spp. (Moraceae). Vernacular names applied include arah (Sabah) and kayuara (Sabah). Major species include F. callosa, F. fistulosa, F. lamponga, F. magnoliifolia, F. microcarpa, F. racemosa, F. sundaica, F. superba, F. tinctoria, F. variegata, F. vasculosa, F. virens and F. viridicarpa. The sapwood is not differentiated from the heartwood, which is light yellow-brown or in various shades of yellow to pink-grey.Also known as Fig (India); Ara, Bunut, Karet and Kundang (Indonesia); Deua kiang, Mai deaua kham and Mai do (Laos); Nyaung (Myanmar); Papua New Guinea fig (Papua New Guinea);Balete (Philippines); Sai (Thailand); and Chi da and Sung (Vietnam)."
                                          },
                                          {
                                          "id": "30",
                                          "title": "Balek Angin",
                                          "description": "The common Malaysian name for the timber of Mallotus spp. (Euphorbiaceae). Vernacular names applied include balek angin bopeng (Peninsular Malaysia), enserai (Sarawak), mallotus (Sabah) with various epithets, perupok (Peninsular Malaysia), selung apid (Sabah), serapoh (Peninsular Malaysia), singin (Sarawak) and ulas (Sabah). Major species include M. leucodermis, M. miquelianus, M. muticus and M. wrayi. The sapwood is not differentiated from the heartwood, which is straw-coloured.Also known as Kamala (Australia); Raini (India); Balek angin, Biraki, Ki mejong, Kolimama poete, Morotokoelo, Ota mewoeloe, Tofa, Towoela and Tunbuwat (Indonesia); Banato, Hinlaumo and Tula tula(Philippines); and Vang (Vietnam)."
                                          },
                                          {
                                          "id": "31",
                                          "title": "Bebuta",
                                          "description": "The common Malaysian name for the timber of Excoecaria spp. (Euphorbiaceae). Vernacular names applied include buta-buta (Peninsular Malaysia and Sabah). Only one species attains timber size, viz. E. agallocha. The straw-coloured sapwood is normally not differentiated from the heartwood, which is pink-white to pale brown in colour.Also known as Geon (India); Bintaos laut, Kokoboeta, Menengan and Penggung (Indonesia); Gewa (Pakistan); Buta-buta (Philippines); Tatum (Thailand); and Gia (Vietnam)."
                                          },
                                          {
                                          "id": "32",
                                          "title": "Berangan",
                                          "description": "The Standard Malaysian Name for the timber of Castanopsis spp. (Fagaceae). Vernacular names applied include berangan (Peninsular Malaysia, Sabah and Sarawak) with various epithets, kogopon (Sabah), maruwit (Sarawak) and various other localised names too numerous to be listed here. Major species include C. borneensis, C. buruana, C. clemensii, C.curtisii, C. endertii, C. evansii, C. foxworthyi, C. fulva, C. hypophoenicea, C. inermis, C. javanica, C. malaccensis, C.microphylla, C. motleyana, C. oviformis, C. paucispina, C. psilophylla, C. rhamnifolia and C. schefferiana. The sapwood is light brown, often with a greenish tinge and sharply defined from the heartwood, which is dark brown or dark red-brown.Also know as Indian chestnut (India); Saninten (Indonesia); Fan, Ko and Ko deng (Laos); Katia (Mynmar); New Guinea oak (Papua New Guinea); Gasa and Philippines chestnut (Philippines); Khoduiy, Kholaem, Ko and Ko nam (Thailand); and Ca-oi (Vietnam)."
                                          },
                                          {
                                          "id": "33",
                                          "title": "Binuang",
                                          "description": "The Standard Malaysian Name for the timber of Octomeles sumatrana (Datiscaceae). Vernacular name applied appears to be rather uniform in that only binuang is used throughout the country. Only one species has been recorded in the country. The sapwood is white with a greyish tinge and is moderately sharply defined from the heartwood which is buff to pale brown or sometimes pinkish brown.Also known as Banuang, Benoea, Benuang, Binuang bini and Winuang (Indonesia); Erima, Ilimo and Irima (Papua New Guinea); and Barong, Barousan, Bilus and Binuang (Philippines)."
                                          },
                                          {
                                          "id": "34",
                                          "title": "Dedali",
                                          "description": "The Standard Malaysian Name as well as the ASEAN Standard name for the timber of Strombosia javanica (Olacaceae). Vernacular names applied include bayam badak (Kedah, Perak and Pahang) and belian landak (Sarawak). This is a monotypic timber. The sapwood is lighter in colour than the heartwood and is moderately sharply defined from the heartwood, which is pale yellow with an olive-brown tinge, darkening to light orange-brown.Also known as Entelung and Kayu Kacang (Indonesia); and Banata (Myanmar)."
                                          },
                                          {
                                          "id": "35",
                                          "title": "Gaham Badak",
                                          "description": "The common Malaysian name for the timber of Blumeodendron spp. (Euphorbiaceae). The ASEAN Standard Name for the timber, which is of Indonesian origin, is TENGKURUNG. Vernacular names applied to the timber include gangulang (Sabah), gelugor hutan (Peninsular Malaysia), medang lempong (Peninsular Malaysia) and merbulan (Sarawak). Major species include B. kurzii and B. tokbrai. The heartwood, which is light brown in colour, is not distinct from the lighter coloured sapwood. Occasionally, a corewood of darker brown with black streaks is produced.Also known as Tengkurung (Indonesia); and Lindog (Philippines)."
                                          }
                                          ],
                                "childern": []
                                },
                                {
                                "id": "2.2",
                                "title": "Planing  ",
                                "isParent": "true",
                                "Items": [],
                                "childern": [
                                             {
                                             "id": "2.2.1",
                                             "isParent": "false",
                                             "title": "Column – heavy duty",
                                             "items": [
                                                       {
                                                       "id": "1",
                                                       "titile": "",
                                                       "description": ""
                                                       },
                                                       {
                                                       "id": "2",
                                                       "titile": "",
                                                       "description": ""
                                                       },
                                                       {
                                                       "id": "3",
                                                       "titile": "",
                                                       "description": ""
                                                       },
                                                       {
                                                       "id": "4",
                                                       "titile": "",
                                                       "description": ""
                                                       },
                                                       {
                                                       "id": "5",
                                                       "titile": "",
                                                       "description": ""
                                                       }
                                                       ]
                                             },
                                             {
                                             "id": "1.2.2",
                                             "title": "Column – light duty",
                                             "isParent": "false",
                                             "items": [
                                                       {
                                                       "id": "1",
                                                       "titile": "",
                                                       "description": ""
                                                       },
                                                       {
                                                       "id": "2",
                                                       "titile": "",
                                                       "description": ""
                                                       },
                                                       {
                                                       "id": "3",
                                                       "titile": "",
                                                       "description": ""
                                                       },
                                                       {
                                                       "id": "4",
                                                       "titile": "",
                                                       "description": ""
                                                       },
                                                       {
                                                       "id": "5",
                                                       "titile": "",
                                                       "description": ""
                                                       }
                                                       ]
                                             },
                                             {
                                             "id": "1.2.3",
                                             "title": "Door and window frames and sills",
                                             "isParent": "false",
                                             "items": []
                                             },
                                             {
                                             "id": "1.2.4",
                                             "title": "Flooring – general",
                                             "isParent": "false",
                                             "items": [
                                                       {
                                                       "id": "1",
                                                       "titile": "",
                                                       "description": ""
                                                       },
                                                       {
                                                       "id": "2",
                                                       "titile": "",
                                                       "description": ""
                                                       },
                                                       {
                                                       "id": "3",
                                                       "titile": "",
                                                       "description": ""
                                                       },
                                                       {
                                                       "id": "4",
                                                       "titile": "",
                                                       "description": ""
                                                       },
                                                       {
                                                       "id": "5",
                                                       "titile": "",
                                                       "description": ""
                                                       }
                                                       ]
                                             },
                                             {
                                             "id": "1.2.5",
                                             "title": "Flooring – heavy traffic",
                                             "isParent": "false",
                                             "items": []
                                             },
                                             {
                                             "id": "1.2.6",
                                             "title": "Foundation piling",
                                             "isParent": "false",
                                             "items": [
                                                       {
                                                       "id": "1",
                                                       "titile": "",
                                                       "description": ""
                                                       },
                                                       {
                                                       "id": "2",
                                                       "titile": "",
                                                       "description": ""
                                                       },
                                                       {
                                                       "id": "3",
                                                       "titile": "",
                                                       "description": ""
                                                       },
                                                       {
                                                       "id": "4",
                                                       "titile": "",
                                                       "description": ""
                                                       },
                                                       {
                                                       "id": "5",
                                                       "titile": "",
                                                       "description": ""
                                                       }
                                                       ]
                                             }
                                             ]
                                },
                                {
                                "id": "2.3",
                                "title": "Sawing",
                                "isParent": "false",
                                "Items": [
                                          {
                                          "id": "8",
                                          "title": "Baru",
                                          "description": "The common Malaysian name for the timber of Hibiscus spp. and Thespesia populnea (Malvaceae). Vernacular names applied include baru-baru (Peninsular Malaysia), baru laut (Sabah), bebaru (Peninsular Malaysia), bebaru bulu (Peninsular Malaysia), kali bang-bang (Sabah), kangsar (Peninsular Malaysia), langkubing (Sarawak), randog (Sabah) and tutor (Peninsular Malaysia). Major species include Hibiscus borneensis, H. campylosiphon, H. floccosus, H. macrophyllus, H. tiliaceus; and Thespesia populnea. The sapwood ranges from white to light yellow and is not defined to sharply defined from the heartwood, which varies from light yellow, light grey-brown, grey-black, purple black to red brown.Also known as Baru, Bontoe, Waru, Waru gunong and Waroe (Indonesia); Silver hibiscus (Papua New Guinea); Gummamela de arana and Malubago (Philippines); and Ehaba (Thailand)."
                                          },
                                          {
                                          "id": "9",
                                          "title": "Chengal",
                                          "description": "The common Malaysian name for the timber of Mallotus spp. (Euphorbiaceae). Vernacular names applied include balek angin bopeng (Peninsular Malaysia), enserai (Sarawak), mallotus (Sabah) with various epithets, perupok (Peninsular Malaysia), selung apid (Sabah), serapoh (Peninsular Malaysia), singin (Sarawak) and ulas (Sabah). Major species include M. leucodermis, M. miquelianus, M. muticus and M. wrayi. The sapwood is not differentiated from the heartwood, which is straw-coloured.Also known as Kamala (Australia); Raini (India); Balek angin, Biraki, Ki mejong, Kolimama poete, Morotokoelo, Ota mewoeloe, Tofa, Towoela and Tunbuwat (Indonesia); Banato, Hinlaumo and Tula tula(Philippines); and Vang (Vietnam)."
                                          },
                                          {
                                          "id": "10",
                                          "title": "Dedap",
                                          "description": "The common Malaysian name for the timber of Excoecaria spp. (Euphorbiaceae). Vernacular names applied include buta-buta (Peninsular Malaysia and Sabah). Only one species attains timber size, viz. E. agallocha. The straw-coloured sapwood is normally not differentiated from the heartwood, which is pink-white to pale brown in colour.Also known as Geon (India); Bintaos laut, Kokoboeta, Menengan and Penggung (Indonesia); Gewa (Pakistan); Buta-buta (Philippines); Tatum (Thailand); and Gia (Vietnam)."
                                          },
                                          {
                                          "id": "11",
                                          "title": "Derum",
                                          "description": "The Standard Malaysian Name for the timber of Castanopsis spp. (Fagaceae). Vernacular names applied include berangan (Peninsular Malaysia, Sabah and Sarawak) with various epithets, kogopon (Sabah), maruwit (Sarawak) and various other localised names too numerous to be listed here. Major species include C. borneensis, C. buruana, C. clemensii, C.curtisii, C. endertii, C. evansii, C. foxworthyi, C. fulva, C. hypophoenicea, C. inermis, C. javanica, C. malaccensis, C.microphylla, C. motleyana, C. oviformis, C. paucispina, C. psilophylla, C. rhamnifolia and C. schefferiana. The sapwood is light brown, often with a greenish tinge and sharply defined from the heartwood, which is dark brown or dark red-brown.Also know as Indian chestnut (India); Saninten (Indonesia); Fan, Ko and Ko deng (Laos); Katia (Mynmar); New Guinea oak (Papua New Guinea); Gasa and Philippines chestnut (Philippines); Khoduiy, Kholaem, Ko and Ko nam (Thailand); and Ca-oi (Vietnam)."
                                          },
                                          {
                                          "id": "12",
                                          "title": "Gading",
                                          "description": "The common Malaysian name for the timber of Excoecaria spp. (Euphorbiaceae). Vernacular names applied include buta-buta (Peninsular Malaysia and Sabah). Only one species attains timber size, viz. E. agallocha. The straw-coloured sapwood is normally not differentiated from the heartwood, which is pink-white to pale brown in colour.Also known as Geon (India); Bintaos laut, Kokoboeta, Menengan and Penggung (Indonesia); Gewa (Pakistan); Buta-buta (Philippines); Tatum (Thailand); and Gia (Vietnam)."
                                          },
                                          {
                                          "id": "13",
                                          "title": "Jelutong",
                                          "description": "The common Malaysian name for the timber of Excoecaria spp. (Euphorbiaceae). Vernacular names applied include buta-buta (Peninsular Malaysia and Sabah). Only one species attains timber size, viz. E. agallocha. The straw-coloured sapwood is normally not differentiated from the heartwood, which is pink-white to pale brown in colour.Also known as Geon (India); Bintaos laut, Kokoboeta, Menengan and Penggung (Indonesia); Gewa (Pakistan); Buta-buta (Philippines); Tatum (Thailand); and Gia (Vietnam)."
                                          },
                                          {
                                          "id": "14",
                                          "title": "Jelutong Pipit",
                                          "description": "The common Malaysian name for the timber of Excoecaria spp. (Euphorbiaceae). Vernacular names applied include buta-buta (Peninsular Malaysia and Sabah). Only one species attains timber size, viz. E. agallocha. The straw-coloured sapwood is normally not differentiated from the heartwood, which is pink-white to pale brown in colour.Also known as Geon (India); Bintaos laut, Kokoboeta, Menengan and Penggung (Indonesia); Gewa (Pakistan); Buta-buta (Philippines); Tatum (Thailand); and Gia (Vietnam)."
                                          }
                                          ],
                                "childern": []
                                },
                                {
                                "id": "2.4",
                                "title": "Turning ",
                                "isParent": "true",
                                "Items": [],
                                "childern": []
                                }
                                ]
                   },
                   {
                   "id": "3",
                   "level": 1,
                   "title": "Nailing Property",
                   "isParent": "true",
                   "childern": [
                   {},
                   {},
                   {},
                   {}
                   ]
                   },
                   {
                   "id": "4",
                   "level": 1,
                   "title": "Physical Properties",
                   "isParent": "true",
                   "childern": [
                   {},
                   {},
                   {},
                   {}
                   ]
                   },
                   {
                   "id": "5",
                   "level": 1,
                   "title": "Strength",
                   "isParent": "true",
                   "childern": [
                   {},
                   {},
                   {},
                   {}
                   ]
                   },
                   {
                   "id": "6",
                   "level": 1,
                   "title": "Strength Groups",
                   "isParent": "true",
                   "childern": [
                   {},
                   {},
                   {},
                   {}
                   ]
                   },
                   {
                   "id": "7",
                   "level": 1,
                   "title": "Timber Movement",
                   "isParent": "true",
                   "childern": [
                   {},
                   {},
                   {},
                   {}
                   ]
                   }
                   ]
}
